binalyzer_wasm/__init__.py
binalyzer_wasm/extension.py
binalyzer_wasm/wasm.py
binalyzer_wasm-1.0.0.data/data/CHANGELOG.md
binalyzer_wasm-1.0.0.dist-info/AUTHORS
binalyzer_wasm-1.0.0.dist-info/LICENSE.rst
binalyzer_wasm-1.0.0.dist-info/METADATA
binalyzer_wasm-1.0.0.dist-info/WHEEL
binalyzer_wasm-1.0.0.dist-info/top_level.txt
binalyzer_wasm-1.0.0.dist-info/RECORD
