Metadata-Version: 2.1
Name: binalyzer-wasm
Version: 1.0.0
Summary: Binary Data Analyzer
Home-page: https://binalyzer.denisvasilik.com
Author: Denis Vasilìk
Author-email: contact@denisvasilik.com
License: UNKNOWN
Project-URL: Bug Tracker, https://github.com/denisvasilik/binalyzer/issues/
Project-URL: Documentation, https://binalyzer.readthedocs.io/en/latest/
Project-URL: Source Code, https://github.com/denisvasilik/binalyzer/
Platform: UNKNOWN
Classifier: Programming Language :: Python :: 3.6
Classifier: Operating System :: POSIX :: Linux
Requires-Dist: binalyzer
Requires-Dist: leb128 (>=1.0.2)
